git2doc/__init__.py
git2doc/loader.py
git2vec/__init__.py
git2vec/loader.py
git2vec/vectordb.py
git2doc-0.2.4.dist-info/METADATA
git2doc-0.2.4.dist-info/WHEEL
git2doc-0.2.4.dist-info/top_level.txt
git2doc-0.2.4.dist-info/RECORD
